{
  "@context":"http://iiif.io/api/presentation/2/context.json",
  "@id":"http://fauvel.archivengine.com/list/fro/14v.json",
  "@type":"sc:AnnotationList",
  "resources": [
    
    {
      "@id": "14v-fro-1635",
      "@type":"oa:Annotation",
      "motivation":"sc:painting",
      "resource": {
        "@id": "14v-fro-1635-text",
        "@type": "dctypes:Text",
        "format": "text/plain",
        "chars": "AAprés se sist Varieté",
        "language": "fro"
      },
      "on": "http://fauvel.archivengine.com/canvas/14v#xywh=1197,756,1197,111"
    },
    
    {
      "@id": "14v-fro-1636",
      "@type":"oa:Annotation",
      "motivation":"sc:painting",
      "resource": {
        "@id": "14v-fro-1636-text",
        "@type": "dctypes:Text",
        "format": "text/plain",
        "chars": "Qui en son dos avait geté",
        "language": "fro"
      },
      "on": "http://fauvel.archivengine.com/canvas/14v#xywh=1197,867,1197,111"
    },
    
    {
      "@id": "14v-fro-1637",
      "@type":"oa:Annotation",
      "motivation":"sc:painting",
      "resource": {
        "@id": "14v-fro-1637-text",
        "@type": "dctypes:Text",
        "format": "text/plain",
        "chars": "Un mantel fourré de penthere",
        "language": "fro"
      },
      "on": "http://fauvel.archivengine.com/canvas/14v#xywh=1197,978,1197,111"
    },
    
    {
      "@id": "14v-fro-1638",
      "@type":"oa:Annotation",
      "motivation":"sc:painting",
      "resource": {
        "@id": "14v-fro-1638-text",
        "@type": "dctypes:Text",
        "format": "text/plain",
        "chars": "Fait de variable matere.",
        "language": "fro"
      },
      "on": "http://fauvel.archivengine.com/canvas/14v#xywh=1197,1089,1197,111"
    },
    
    {
      "@id": "14v-fro-1639",
      "@type":"oa:Annotation",
      "motivation":"sc:painting",
      "resource": {
        "@id": "14v-fro-1639-text",
        "@type": "dctypes:Text",
        "format": "text/plain",
        "chars": "Et cele qui toust se remue",
        "language": "fro"
      },
      "on": "http://fauvel.archivengine.com/canvas/14v#xywh=1197,1200,1197,111"
    },
    
    {
      "@id": "14v-fro-1640",
      "@type":"oa:Annotation",
      "motivation":"sc:painting",
      "resource": {
        "@id": "14v-fro-1640-text",
        "@type": "dctypes:Text",
        "format": "text/plain",
        "chars": "De chanjant est touz jours vestue :",
        "language": "fro"
      },
      "on": "http://fauvel.archivengine.com/canvas/14v#xywh=1197,1311,1197,111"
    },
    
    {
      "@id": "14v-fro-1641",
      "@type":"oa:Annotation",
      "motivation":"sc:painting",
      "resource": {
        "@id": "14v-fro-1641-text",
        "@type": "dctypes:Text",
        "format": "text/plain",
        "chars": "Une chose dit, mais du faire",
        "language": "fro"
      },
      "on": "http://fauvel.archivengine.com/canvas/14v#xywh=1197,1422,1197,111"
    },
    
    {
      "@id": "14v-fro-1642",
      "@type":"oa:Annotation",
      "motivation":"sc:painting",
      "resource": {
        "@id": "14v-fro-1642-text",
        "@type": "dctypes:Text",
        "format": "text/plain",
        "chars": "N'est riens fors que tout au contraire,",
        "language": "fro"
      },
      "on": "http://fauvel.archivengine.com/canvas/14v#xywh=1197,1533,1197,111"
    },
    
    {
      "@id": "14v-fro-1643",
      "@type":"oa:Annotation",
      "motivation":"sc:painting",
      "resource": {
        "@id": "14v-fro-1643-text",
        "@type": "dctypes:Text",
        "format": "text/plain",
        "chars": "Et par sa belle contenance",
        "language": "fro"
      },
      "on": "http://fauvel.archivengine.com/canvas/14v#xywh=1197,1644,1197,111"
    },
    
    {
      "@id": "14v-fro-1644",
      "@type":"oa:Annotation",
      "motivation":"sc:painting",
      "resource": {
        "@id": "14v-fro-1644-text",
        "@type": "dctypes:Text",
        "format": "text/plain",
        "chars": "Est elle appelee Inconstance.",
        "language": "fro"
      },
      "on": "http://fauvel.archivengine.com/canvas/14v#xywh=1197,1755,1197,111"
    },
    
    {
      "@id": "14v-fro-1645",
      "@type":"oa:Annotation",
      "motivation":"sc:painting",
      "resource": {
        "@id": "14v-fro-1645-text",
        "@type": "dctypes:Text",
        "format": "text/plain",
        "chars": "AAprés fu Doubleté assise",
        "language": "fro"
      },
      "on": "http://fauvel.archivengine.com/canvas/14v#xywh=1207,2761,1145,106"
    },
    
    {
      "@id": "14v-fro-1646",
      "@type":"oa:Annotation",
      "motivation":"sc:painting",
      "resource": {
        "@id": "14v-fro-1646-text",
        "@type": "dctypes:Text",
        "format": "text/plain",
        "chars": "Qui touz jours a s'entente mise",
        "language": "fro"
      },
      "on": "http://fauvel.archivengine.com/canvas/14v#xywh=1207,2867,1145,106"
    },
    
    {
      "@id": "14v-fro-1647",
      "@type":"oa:Annotation",
      "motivation":"sc:painting",
      "resource": {
        "@id": "14v-fro-1647-text",
        "@type": "dctypes:Text",
        "format": "text/plain",
        "chars": "A dire sa parole double",
        "language": "fro"
      },
      "on": "http://fauvel.archivengine.com/canvas/14v#xywh=1207,2973,1145,106"
    },
    
    {
      "@id": "14v-fro-1648",
      "@type":"oa:Annotation",
      "motivation":"sc:painting",
      "resource": {
        "@id": "14v-fro-1648-text",
        "@type": "dctypes:Text",
        "format": "text/plain",
        "chars": "Ou qui soit d'entencion double.",
        "language": "fro"
      },
      "on": "http://fauvel.archivengine.com/canvas/14v#xywh=1207,3079,1145,106"
    },
    
    {
      "@id": "14v-fro-1649",
      "@type":"oa:Annotation",
      "motivation":"sc:painting",
      "resource": {
        "@id": "14v-fro-1649-text",
        "@type": "dctypes:Text",
        "format": "text/plain",
        "chars": "Lez lui tint Fausseté son siege",
        "language": "fro"
      },
      "on": "http://fauvel.archivengine.com/canvas/14v#xywh=1207,3185,1145,106"
    },
    
    {
      "@id": "14v-fro-1650",
      "@type":"oa:Annotation",
      "motivation":"sc:painting",
      "resource": {
        "@id": "14v-fro-1650-text",
        "@type": "dctypes:Text",
        "format": "text/plain",
        "chars": "Qui est plus fausse que n'est liege :",
        "language": "fro"
      },
      "on": "http://fauvel.archivengine.com/canvas/14v#xywh=1207,3291,1145,106"
    },
    
    {
      "@id": "14v-fro-1651",
      "@type":"oa:Annotation",
      "motivation":"sc:painting",
      "resource": {
        "@id": "14v-fro-1651-text",
        "@type": "dctypes:Text",
        "format": "text/plain",
        "chars": "C'est celle ou l'en aucun bien cuide,",
        "language": "fro"
      },
      "on": "http://fauvel.archivengine.com/canvas/14v#xywh=1207,3397,1145,106"
    },
    
    {
      "@id": "14v-fro-1652",
      "@type":"oa:Annotation",
      "motivation":"sc:painting",
      "resource": {
        "@id": "14v-fro-1652-text",
        "@type": "dctypes:Text",
        "format": "text/plain",
        "chars": "Mes elle est desloial et vuide.",
        "language": "fro"
      },
      "on": "http://fauvel.archivengine.com/canvas/14v#xywh=1207,3503,1145,106"
    },
    
    {
      "@id": "14v-fro-1653",
      "@type":"oa:Annotation",
      "motivation":"sc:painting",
      "resource": {
        "@id": "14v-fro-1653-text",
        "@type": "dctypes:Text",
        "format": "text/plain",
        "chars": "AAmprés li sist Ingratitude",
        "language": "fro"
      },
      "on": "http://fauvel.archivengine.com/canvas/14v#xywh=1218,4504,1186,105"
    },
    
    {
      "@id": "14v-fro-1654",
      "@type":"oa:Annotation",
      "motivation":"sc:painting",
      "resource": {
        "@id": "14v-fro-1654-text",
        "@type": "dctypes:Text",
        "format": "text/plain",
        "chars": "Qui est tres mauvese et tres rude",
        "language": "fro"
      },
      "on": "http://fauvel.archivengine.com/canvas/14v#xywh=1218,4609,1186,105"
    },
    
    {
      "@id": "14v-fro-1655",
      "@type":"oa:Annotation",
      "motivation":"sc:painting",
      "resource": {
        "@id": "14v-fro-1655-text",
        "@type": "dctypes:Text",
        "format": "text/plain",
        "chars": "Car el ne veult nul recognoistre",
        "language": "fro"
      },
      "on": "http://fauvel.archivengine.com/canvas/14v#xywh=1218,4714,1186,105"
    },
    
    {
      "@id": "14v-fro-1656",
      "@type":"oa:Annotation",
      "motivation":"sc:painting",
      "resource": {
        "@id": "14v-fro-1656-text",
        "@type": "dctypes:Text",
        "format": "text/plain",
        "chars": "Qui painne ait mis en lui acroistre :",
        "language": "fro"
      },
      "on": "http://fauvel.archivengine.com/canvas/14v#xywh=1218,4819,1186,105"
    },
    
    {
      "@id": "14v-fro-1657",
      "@type":"oa:Annotation",
      "motivation":"sc:painting",
      "resource": {
        "@id": "14v-fro-1657-text",
        "@type": "dctypes:Text",
        "format": "text/plain",
        "chars": "En toutes cours soit condempnee",
        "language": "fro"
      },
      "on": "http://fauvel.archivengine.com/canvas/14v#xywh=1218,4924,1186,105"
    },
    
    {
      "@id": "14v-fro-1658",
      "@type":"oa:Annotation",
      "motivation":"sc:painting",
      "resource": {
        "@id": "14v-fro-1658-text",
        "@type": "dctypes:Text",
        "format": "text/plain",
        "chars": "Car el fut de male eure nee !",
        "language": "fro"
      },
      "on": "http://fauvel.archivengine.com/canvas/14v#xywh=1218,5029,1186,105"
    },
    
    {
      "@id": "14v-fro-1659",
      "@type":"oa:Annotation",
      "motivation":"sc:painting",
      "resource": {
        "@id": "14v-fro-1659-text",
        "@type": "dctypes:Text",
        "format": "text/plain",
        "chars": "EEmprés li se sist Vilanie",
        "language": "fro"
      },
      "on": "http://fauvel.archivengine.com/canvas/14v#xywh=3853,798,1082,108"
    },
    
    {
      "@id": "14v-fro-1660",
      "@type":"oa:Annotation",
      "motivation":"sc:painting",
      "resource": {
        "@id": "14v-fro-1660-text",
        "@type": "dctypes:Text",
        "format": "text/plain",
        "chars": "En estat de chevalerie ;",
        "language": "fro"
      },
      "on": "http://fauvel.archivengine.com/canvas/14v#xywh=3853,906,1082,108"
    },
    
    {
      "@id": "14v-fro-1661",
      "@type":"oa:Annotation",
      "motivation":"sc:painting",
      "resource": {
        "@id": "14v-fro-1661-text",
        "@type": "dctypes:Text",
        "format": "text/plain",
        "chars": "Mes a savoir vraie noblesce",
        "language": "fro"
      },
      "on": "http://fauvel.archivengine.com/canvas/14v#xywh=3853,1014,1082,108"
    },
    
    {
      "@id": "14v-fro-1662",
      "@type":"oa:Annotation",
      "motivation":"sc:painting",
      "resource": {
        "@id": "14v-fro-1662-text",
        "@type": "dctypes:Text",
        "format": "text/plain",
        "chars": "Ne maintient son cueur ne adrece.",
        "language": "fro"
      },
      "on": "http://fauvel.archivengine.com/canvas/14v#xywh=3853,1122,1082,108"
    },
    
    {
      "@id": "14v-fro-1663",
      "@type":"oa:Annotation",
      "motivation":"sc:painting",
      "resource": {
        "@id": "14v-fro-1663-text",
        "@type": "dctypes:Text",
        "format": "text/plain",
        "chars": "Mais s'ele fust fille de bon pere,",
        "language": "fro"
      },
      "on": "http://fauvel.archivengine.com/canvas/14v#xywh=3853,1230,1082,108"
    },
    
    {
      "@id": "14v-fro-1664",
      "@type":"oa:Annotation",
      "motivation":"sc:painting",
      "resource": {
        "@id": "14v-fro-1664-text",
        "@type": "dctypes:Text",
        "format": "text/plain",
        "chars": "Droit fust qu'aucun bien en li pere !",
        "language": "fro"
      },
      "on": "http://fauvel.archivengine.com/canvas/14v#xywh=3853,1338,1082,108"
    },
    
    {
      "@id": "14v-fro-1665",
      "@type":"oa:Annotation",
      "motivation":"sc:painting",
      "resource": {
        "@id": "14v-fro-1665-text",
        "@type": "dctypes:Text",
        "format": "text/plain",
        "chars": "Elle cuide estre noble et sage",
        "language": "fro"
      },
      "on": "http://fauvel.archivengine.com/canvas/14v#xywh=3853,1446,1082,108"
    },
    
    {
      "@id": "14v-fro-1666",
      "@type":"oa:Annotation",
      "motivation":"sc:painting",
      "resource": {
        "@id": "14v-fro-1666-text",
        "@type": "dctypes:Text",
        "format": "text/plain",
        "chars": "Pour ce qu'elle a grant heritage,",
        "language": "fro"
      },
      "on": "http://fauvel.archivengine.com/canvas/14v#xywh=3853,1554,1082,108"
    },
    
    {
      "@id": "14v-fro-1667",
      "@type":"oa:Annotation",
      "motivation":"sc:painting",
      "resource": {
        "@id": "14v-fro-1667-text",
        "@type": "dctypes:Text",
        "format": "text/plain",
        "chars": "Mais elle se deçoit et meserre",
        "language": "fro"
      },
      "on": "http://fauvel.archivengine.com/canvas/14v#xywh=3853,1662,1082,108"
    },
    
    {
      "@id": "14v-fro-1668",
      "@type":"oa:Annotation",
      "motivation":"sc:painting",
      "resource": {
        "@id": "14v-fro-1668-text",
        "@type": "dctypes:Text",
        "format": "text/plain",
        "chars": "Car noblesce n'est pas pour terre,",
        "language": "fro"
      },
      "on": "http://fauvel.archivengine.com/canvas/14v#xywh=3853,1770,1082,108"
    },
    
    {
      "@id": "14v-fro-1669",
      "@type":"oa:Annotation",
      "motivation":"sc:painting",
      "resource": {
        "@id": "14v-fro-1669-text",
        "@type": "dctypes:Text",
        "format": "text/plain",
        "chars": "Ains est de cueur en homme enté",
        "language": "fro"
      },
      "on": "http://fauvel.archivengine.com/canvas/14v#xywh=3853,1878,1082,108"
    },
    
    {
      "@id": "14v-fro-1670",
      "@type":"oa:Annotation",
      "motivation":"sc:painting",
      "resource": {
        "@id": "14v-fro-1670-text",
        "@type": "dctypes:Text",
        "format": "text/plain",
        "chars": "Qui est de noble meurs renté ;",
        "language": "fro"
      },
      "on": "http://fauvel.archivengine.com/canvas/14v#xywh=3853,1986,1082,108"
    },
    
    {
      "@id": "14v-fro-1671",
      "@type":"oa:Annotation",
      "motivation":"sc:painting",
      "resource": {
        "@id": "14v-fro-1671-text",
        "@type": "dctypes:Text",
        "format": "text/plain",
        "chars": "Es quex ceus qui sont ententis",
        "language": "fro"
      },
      "on": "http://fauvel.archivengine.com/canvas/14v#xywh=3853,2094,1082,108"
    },
    
    {
      "@id": "14v-fro-1672",
      "@type":"oa:Annotation",
      "motivation":"sc:painting",
      "resource": {
        "@id": "14v-fro-1672-text",
        "@type": "dctypes:Text",
        "format": "text/plain",
        "chars": "Sont tres nobles et tres gentis.",
        "language": "fro"
      },
      "on": "http://fauvel.archivengine.com/canvas/14v#xywh=3853,2202,1082,108"
    },
    
    {
      "@id": "14v-fro-1673",
      "@type":"oa:Annotation",
      "motivation":"sc:painting",
      "resource": {
        "@id": "14v-fro-1673-text",
        "@type": "dctypes:Text",
        "format": "text/plain",
        "chars": "De noble homme tieng et tendré",
        "language": "fro"
      },
      "on": "http://fauvel.archivengine.com/canvas/14v#xywh=3853,2310,1082,108"
    },
    
    {
      "@id": "14v-fro-1674",
      "@type":"oa:Annotation",
      "motivation":"sc:painting",
      "resource": {
        "@id": "14v-fro-1674-text",
        "@type": "dctypes:Text",
        "format": "text/plain",
        "chars": "Qu'il est' de mal sanc engendré",
        "language": "fro"
      },
      "on": "http://fauvel.archivengine.com/canvas/14v#xywh=3853,2418,1082,108"
    },
    
    {
      "@id": "14v-fro-1675",
      "@type":"oa:Annotation",
      "motivation":"sc:painting",
      "resource": {
        "@id": "14v-fro-1675-text",
        "@type": "dctypes:Text",
        "format": "text/plain",
        "chars": "Ou né en pechié d'avoutire,",
        "language": "fro"
      },
      "on": "http://fauvel.archivengine.com/canvas/14v#xywh=3853,2526,1082,108"
    },
    
    {
      "@id": "14v-fro-1676",
      "@type":"oa:Annotation",
      "motivation":"sc:painting",
      "resource": {
        "@id": "14v-fro-1676-text",
        "@type": "dctypes:Text",
        "format": "text/plain",
        "chars": "Quant si ne s'acesme et atire",
        "language": "fro"
      },
      "on": "http://fauvel.archivengine.com/canvas/14v#xywh=3853,2634,1082,108"
    },
    
    {
      "@id": "14v-fro-1677",
      "@type":"oa:Annotation",
      "motivation":"sc:painting",
      "resource": {
        "@id": "14v-fro-1677-text",
        "@type": "dctypes:Text",
        "format": "text/plain",
        "chars": "De nobles faiz par quoi on die",
        "language": "fro"
      },
      "on": "http://fauvel.archivengine.com/canvas/14v#xywh=3853,2742,1082,108"
    },
    
    {
      "@id": "14v-fro-1678",
      "@type":"oa:Annotation",
      "motivation":"sc:painting",
      "resource": {
        "@id": "14v-fro-1678-text",
        "@type": "dctypes:Text",
        "format": "text/plain",
        "chars": "Que vilain ne l'engendra mie.",
        "language": "fro"
      },
      "on": "http://fauvel.archivengine.com/canvas/14v#xywh=3853,2850,1082,108"
    },
    
    {
      "@id": "14v-fro-1679",
      "@type":"oa:Annotation",
      "motivation":"sc:painting",
      "resource": {
        "@id": "14v-fro-1679-text",
        "@type": "dctypes:Text",
        "format": "text/plain",
        "chars": "EEt puis aprÈs sist Angoisseuse",
        "language": "fro"
      },
      "on": "http://fauvel.archivengine.com/canvas/14v#xywh=3843,4021,1029,116"
    },
    
    {
      "@id": "14v-fro-1680",
      "@type":"oa:Annotation",
      "motivation":"sc:painting",
      "resource": {
        "@id": "14v-fro-1680-text",
        "@type": "dctypes:Text",
        "format": "text/plain",
        "chars": "Qui de labourer n'est oiseuse,",
        "language": "fro"
      },
      "on": "http://fauvel.archivengine.com/canvas/14v#xywh=3843,4137,1029,116"
    },
    
    {
      "@id": "14v-fro-1681",
      "@type":"oa:Annotation",
      "motivation":"sc:painting",
      "resource": {
        "@id": "14v-fro-1681-text",
        "@type": "dctypes:Text",
        "format": "text/plain",
        "chars": "Car aus dimanches et aus festes",
        "language": "fro"
      },
      "on": "http://fauvel.archivengine.com/canvas/14v#xywh=3843,4253,1029,116"
    },
    
    {
      "@id": "14v-fro-1682",
      "@type":"oa:Annotation",
      "motivation":"sc:painting",
      "resource": {
        "@id": "14v-fro-1682-text",
        "@type": "dctypes:Text",
        "format": "text/plain",
        "chars": "Fait labourer serjanz et bestes :",
        "language": "fro"
      },
      "on": "http://fauvel.archivengine.com/canvas/14v#xywh=3843,4369,1029,116"
    },
    
    {
      "@id": "14v-fro-1683",
      "@type":"oa:Annotation",
      "motivation":"sc:painting",
      "resource": {
        "@id": "14v-fro-1683-text",
        "@type": "dctypes:Text",
        "format": "text/plain",
        "chars": "Si grant haste a de labourer",
        "language": "fro"
      },
      "on": "http://fauvel.archivengine.com/canvas/14v#xywh=3843,4485,1029,116"
    },
    
    {
      "@id": "14v-fro-1684",
      "@type":"oa:Annotation",
      "motivation":"sc:painting",
      "resource": {
        "@id": "14v-fro-1684-text",
        "@type": "dctypes:Text",
        "format": "text/plain",
        "chars": "Qu'il ne li chaut de Dieu ourer.",
        "language": "fro"
      },
      "on": "http://fauvel.archivengine.com/canvas/14v#xywh=3843,4601,1029,116"
    },
    
    {
      "@id": "14v-fro-1685",
      "@type":"oa:Annotation",
      "motivation":"sc:painting",
      "resource": {
        "@id": "14v-fro-1685-text",
        "@type": "dctypes:Text",
        "format": "text/plain",
        "chars": "Et s'el n'avoit enfant ne fame,",
        "language": "fro"
      },
      "on": "http://fauvel.archivengine.com/canvas/14v#xywh=3843,4717,1029,116"
    },
    
    {
      "@id": "14v-fro-1686",
      "@type":"oa:Annotation",
      "motivation":"sc:painting",
      "resource": {
        "@id": "14v-fro-1686-text",
        "@type": "dctypes:Text",
        "format": "text/plain",
        "chars": "Si vourroit el mener tel game.",
        "language": "fro"
      },
      "on": "http://fauvel.archivengine.com/canvas/14v#xywh=3843,4833,1029,116"
    },
    
    {
      "@id": "14v-fro-1687",
      "@type":"oa:Annotation",
      "motivation":"sc:painting",
      "resource": {
        "@id": "14v-fro-1687-text",
        "@type": "dctypes:Text",
        "format": "text/plain",
        "chars": "Sachez qu'il est nez de mal heure",
        "language": "fro"
      },
      "on": "http://fauvel.archivengine.com/canvas/14v#xywh=3843,4949,1029,116"
    },
    
    {
      "@id": "14v-fro-1688",
      "@type":"oa:Annotation",
      "motivation":"sc:painting",
      "resource": {
        "@id": "14v-fro-1688-text",
        "@type": "dctypes:Text",
        "format": "text/plain",
        "chars": "Qui en tel maniere labeure,",
        "language": "fro"
      },
      "on": "http://fauvel.archivengine.com/canvas/14v#xywh=3843,5065,1029,116"
    },
    
    {
      "@id": "14v-fro-1689",
      "@type":"oa:Annotation",
      "motivation":"sc:painting",
      "resource": {
        "@id": "14v-fro-1689-text",
        "@type": "dctypes:Text",
        "format": "text/plain",
        "chars": "Et l'un et l'autre testament",
        "language": "fro"
      },
      "on": "http://fauvel.archivengine.com/canvas/14v#xywh=3843,5181,1029,116"
    },
    
    {
      "@id": "14v-fro-1690",
      "@type":"oa:Annotation",
      "motivation":"sc:painting",
      "resource": {
        "@id": "14v-fro-1690-text",
        "@type": "dctypes:Text",
        "format": "text/plain",
        "chars": "Le deffendent, se Diex m'ament.",
        "language": "fro"
      },
      "on": "http://fauvel.archivengine.com/canvas/14v#xywh=3843,5297,1029,116"
    },
    
    {
      "@id": "14v-fro-1691",
      "@type":"oa:Annotation",
      "motivation":"sc:painting",
      "resource": {
        "@id": "14v-fro-1691-text",
        "@type": "dctypes:Text",
        "format": "text/plain",
        "chars": "EEntour le sire qui est fauve",
        "language": "fro"
      },
      "on": "http://fauvel.archivengine.com/canvas/14v#xywh=3843,5413,1029,116"
    },
    
    {
      "@id": "14v-fro-1692",
      "@type":"oa:Annotation",
      "motivation":"sc:painting",
      "resource": {
        "@id": "14v-fro-1692-text",
        "@type": "dctypes:Text",
        "format": "text/plain",
        "chars": "Avoit, se Jhesucrist me sauve,",
        "language": "fro"
      },
      "on": "http://fauvel.archivengine.com/canvas/14v#xywh=3843,5529,1029,116"
    },
    
    {
      "@id": "14v-fro-1693",
      "@type":"oa:Annotation",
      "motivation":"sc:painting",
      "resource": {
        "@id": "14v-fro-1693-text",
        "@type": "dctypes:Text",
        "format": "text/plain",
        "chars": "Trop grant foison de sa mesnie ;",
        "language": "fro"
      },
      "on": "http://fauvel.archivengine.com/canvas/14v#xywh=3843,5645,1029,116"
    },
    
    {
      "@id": "14v-fro-1694",
      "@type":"oa:Annotation",
      "motivation":"sc:painting",
      "resource": {
        "@id": "14v-fro-1694-text",
        "@type": "dctypes:Text",
        "format": "text/plain",
        "chars": "Moult i ot bele compaingnie :",
        "language": "fro"
      },
      "on": "http://fauvel.archivengine.com/canvas/14v#xywh=3843,5761,1029,116"
    },
    
    {
      "@id": "14v-fro-1695",
      "@type":"oa:Annotation",
      "motivation":"sc:painting",
      "resource": {
        "@id": "14v-fro-1695-text",
        "@type": "dctypes:Text",
        "format": "text/plain",
        "chars": "Il i fut Barat, Boulerie,",
        "language": "fro"
      },
      "on": "http://fauvel.archivengine.com/canvas/14v#xywh=3843,5877,1029,116"
    },
    
    {
      "@id": "14v-fro-1696",
      "@type":"oa:Annotation",
      "motivation":"sc:painting",
      "resource": {
        "@id": "14v-fro-1696-text",
        "@type": "dctypes:Text",
        "format": "text/plain",
        "chars": "Faussart, Tripot et Tricherie",
        "language": "fro"
      },
      "on": "http://fauvel.archivengine.com/canvas/14v#xywh=3843,5993,1029,116"
    }
    
  ]
}
